timeti/__init__.py
timeti/clockface.py
timeti/stopwatch.py
timeti-0.4.0.dist-info/LICENSE
timeti-0.4.0.dist-info/METADATA
timeti-0.4.0.dist-info/WHEEL
timeti-0.4.0.dist-info/top_level.txt
timeti-0.4.0.dist-info/RECORD
