Metadata-Version: 2.1
Name: timeti
Version: 0.4.0
Summary: Serialize elapsed time of functions, loops and code blocks.
Author-email: Ilia Lazarev <the.ilia.lazarev@gmail.com>
License: MIT License        
Project-URL: Homepage, https://github.com/kephircheek/elapsed-time-logger
Classifier: Programming Language :: Python :: 3
Classifier: License :: OSI Approved :: MIT License
Classifier: Operating System :: OS Independent
Requires-Python: >=3.8
License-File: LICENSE
Provides-Extra: dev
Requires-Dist: mypy ; extra == 'dev'
Requires-Dist: isort[colors] ; extra == 'dev'
Requires-Dist: black ; extra == 'dev'
Requires-Dist: pydocstyle ; extra == 'dev'
Requires-Dist: toml ; extra == 'dev'
